inkext/__init__.py
inkext/css.py
inkext/geomsvg.py
inkext/inkext.py
inkext/inkstall.py
inkext/inksvg.py
inkext/py.typed
inkext/svg.py
utl_inkext-0.2.2.dist-info/LICENSE
utl_inkext-0.2.2.dist-info/METADATA
utl_inkext-0.2.2.dist-info/WHEEL
utl_inkext-0.2.2.dist-info/entry_points.txt
utl_inkext-0.2.2.dist-info/top_level.txt
utl_inkext-0.2.2.dist-info/RECORD
