Metadata-Version: 2.1
Name: utl-inkext
Version: 0.2.2
Summary: Inkscape extension library
Author-email: Claude Zervas <claude@utlco.com>
License: GNU LESSER GENERAL PUBLIC LICENSE
Classifier: Programming Language :: Python :: 3
Requires-Python: >=3.9
License-File: LICENSE
Requires-Dist: lxml
Requires-Dist: tomli
Requires-Dist: packaging
Requires-Dist: typing-extensions
Requires-Dist: utl-geom2d
Provides-Extra: dev
Requires-Dist: pytest ; extra == 'dev'
Requires-Dist: black ; extra == 'dev'
Requires-Dist: ruff ; extra == 'dev'
Requires-Dist: pylint ; extra == 'dev'
Requires-Dist: mypy ; extra == 'dev'
Requires-Dist: lxml-stubs ; extra == 'dev'
Requires-Dist: sphinx ; extra == 'dev'
Requires-Dist: utl-sphinx-theme ; extra == 'dev'
Provides-Extra: test
Requires-Dist: pytest ; extra == 'test'
